snowpipe_cli/__init__.py
snowpipe_cli/__main__.py
snowpipe_cli/snowpipe.py
snowpipe_cli-0.0.2rc4.dist-info/LICENSE
snowpipe_cli-0.0.2rc4.dist-info/METADATA
snowpipe_cli-0.0.2rc4.dist-info/WHEEL
snowpipe_cli-0.0.2rc4.dist-info/entry_points.txt
snowpipe_cli-0.0.2rc4.dist-info/top_level.txt
snowpipe_cli-0.0.2rc4.dist-info/RECORD
