Metadata-Version: 2.1
Name: snowpipe-cli
Version: 0.0.2rc4
Summary: A CLI utility for Snowflake Snowpipe REST APIs
Home-page: https://github.com/phdata/snowpipe-cli
Author: Daniel Pierce
Author-email: paladin2350@gmail.com
License: UNKNOWN
Project-URL: Bug Tracker, https://github.com/phdata/snowpipe-cli/issues
Platform: UNKNOWN
Classifier: Programming Language :: Python :: 3
Classifier: License :: OSI Approved :: Apache Software License
Classifier: Operating System :: OS Independent
Requires-Python: >=3.8
License-File: LICENSE
Requires-Dist: PyYAML (~=5.4.1)
Requires-Dist: snowflake-ingest (~=1.0.3)
Requires-Dist: cryptography (~=3.4.7)
Requires-Dist: snowflake-connector-python (~=2.4.2)
